{
  "vendors": [
    {
      "id": "vendor_0001",
      "userId": "8ZzH3ONSuSpz1IYwJLiLlpooxbIKxPNO",
      "businessName": "TechNova Ventures",
      "status": "active",
      "contactEmail": "vendor1@shopstack.demo",
      "contactPhone": "+15550000001"
    },
    {
      "id": "vendor_0002",
      "userId": "CQUDCefoyYyfpPqbFi4OuzR2XKq0Lbwh",
      "businessName": "StyleCraft LLC",
      "status": "active",
      "contactEmail": "vendor2@shopstack.demo",
      "contactPhone": "+15550000002"
    },
    {
      "id": "vendor_0003",
      "userId": "TidNPzRp37zli5iqJoBQQTGypKqzJGg0",
      "businessName": "HomeWorld Inc",
      "status": "active",
      "contactEmail": "vendor3@shopstack.demo",
      "contactPhone": "+15550000003"
    },
    {
      "id": "vendor_0004",
      "userId": "fuHd3tcUr1SZ0PWHKi9TM3yHv34enu8a",
      "businessName": "GreenPath Farms",
      "status": "active",
      "contactEmail": "vendor4@shopstack.demo",
      "contactPhone": "+15550000004"
    },
    {
      "id": "vendor_0005",
      "userId": "oUP6VlQVSvDF65xAUrIyuvqMxoPsmURL",
      "businessName": "ProFit Athletics",
      "status": "active",
      "contactEmail": "vendor5@shopstack.demo",
      "contactPhone": "+15550000005"
    },
    {
      "id": "vendor_0006",
      "userId": "xUYMejz1mKqSD7smI5snNI3roupLUsJG",
      "businessName": "Bookish Enterprises",
      "status": "active",
      "contactEmail": "vendor6@shopstack.demo",
      "contactPhone": "+15550000006"
    }
  ],
  "shops": [
    {
      "id": "shop_0007",
      "vendorId": "vendor_0001",
      "name": "TechVault Electronics",
      "slug": "techvault-electronics",
      "description": "Premium electronics and gadgets for tech enthusiasts",
      "category": "Electronics",
      "status": "active",
      "logo": "https://picsum.photos/seed/1000/200/200",
      "banner": "https://picsum.photos/seed/1001/1200/400"
    },
    {
      "id": "shop_0061",
      "vendorId": "vendor_0002",
      "name": "StyleHaven Boutique",
      "slug": "stylehaven-boutique",
      "description": "Trendy fashion and apparel for modern lifestyles",
      "category": "Fashion",
      "status": "active",
      "logo": "https://picsum.photos/seed/1022/200/200",
      "banner": "https://picsum.photos/seed/1023/1200/400"
    },
    {
      "id": "shop_0116",
      "vendorId": "vendor_0003",
      "name": "HomeNest Living",
      "slug": "homenest-living",
      "description": "Beautiful home decor and furniture essentials",
      "category": "Home & Living",
      "status": "active",
      "logo": "https://picsum.photos/seed/1044/200/200",
      "banner": "https://picsum.photos/seed/1045/1200/400"
    },
    {
      "id": "shop_0170",
      "vendorId": "vendor_0004",
      "name": "GreenLeaf Organics",
      "slug": "greenleaf-organics",
      "description": "Fresh organic produce and healthy food options",
      "category": "Grocery",
      "status": "active",
      "logo": "https://picsum.photos/seed/1066/200/200",
      "banner": "https://picsum.photos/seed/1067/1200/400"
    },
    {
      "id": "shop_0220",
      "vendorId": "vendor_0005",
      "name": "FitPro Sports",
      "slug": "fitpro-sports",
      "description": "High-performance sports gear and fitness equipment",
      "category": "Sports",
      "status": "active",
      "logo": "https://picsum.photos/seed/1088/200/200",
      "banner": "https://picsum.photos/seed/1089/1200/400"
    },
    {
      "id": "shop_0274",
      "vendorId": "vendor_0006",
      "name": "BookWorm Haven",
      "slug": "bookworm-haven",
      "description": "Curated books and stationery for avid readers",
      "category": "Books",
      "status": "active",
      "logo": "https://picsum.photos/seed/1110/200/200",
      "banner": "https://picsum.photos/seed/1111/1200/400"
    },
    {
      "id": "shop_0323",
      "vendorId": "vendor_0001",
      "name": "PetPals Store",
      "slug": "petpals-store",
      "description": "Everything your furry friends need and love",
      "category": "Pet Supplies",
      "status": "active",
      "logo": "https://picsum.photos/seed/1132/200/200",
      "banner": "https://picsum.photos/seed/1133/1200/400"
    },
    {
      "id": "shop_0373",
      "vendorId": "vendor_0002",
      "name": "BeautyGlow Cosmetics",
      "slug": "beautyglow-cosmetics",
      "description": "Premium skincare and cosmetics collection",
      "category": "Beauty",
      "status": "active",
      "logo": "https://picsum.photos/seed/1154/200/200",
      "banner": "https://picsum.photos/seed/1155/1200/400"
    },
    {
      "id": "shop_0427",
      "vendorId": "vendor_0003",
      "name": "KidZone Toys",
      "slug": "kidzone-toys",
      "description": "Fun and educational toys for children of all ages",
      "category": "Toys",
      "status": "active",
      "logo": "https://picsum.photos/seed/1176/200/200",
      "banner": "https://picsum.photos/seed/1177/1200/400"
    },
    {
      "id": "shop_0477",
      "vendorId": "vendor_0004",
      "name": "GadgetWorld Hub",
      "slug": "gadgetworld-hub",
      "description": "Affordable smart devices and accessories",
      "category": "Electronics",
      "status": "active",
      "logo": "https://picsum.photos/seed/1198/200/200",
      "banner": "https://picsum.photos/seed/1199/1200/400"
    }
  ],
  "categories": [
    {
      "id": "cat_0008",
      "shopId": "shop_0007",
      "name": "Smartphones",
      "slug": "smartphones",
      "description": "Smartphones category for TechVault Electronics",
      "isActive": true,
      "sortOrder": 0
    },
    {
      "id": "cat_0009",
      "shopId": "shop_0007",
      "name": "Laptops",
      "slug": "laptops",
      "description": "Laptops category for TechVault Electronics",
      "isActive": true,
      "sortOrder": 1
    },
    {
      "id": "cat_0010",
      "shopId": "shop_0007",
      "name": "Audio",
      "slug": "audio",
      "description": "Audio category for TechVault Electronics",
      "isActive": true,
      "sortOrder": 2
    },
    {
      "id": "cat_0011",
      "shopId": "shop_0007",
      "name": "Wearables",
      "slug": "wearables",
      "description": "Wearables category for TechVault Electronics",
      "isActive": true,
      "sortOrder": 3
    },
    {
      "id": "cat_0012",
      "shopId": "shop_0007",
      "name": "Accessories",
      "slug": "accessories",
      "description": "Accessories category for TechVault Electronics",
      "isActive": true,
      "sortOrder": 4
    },
    {
      "id": "cat_0062",
      "shopId": "shop_0061",
      "name": "Men's Wear",
      "slug": "men-s-wear",
      "description": "Men's Wear category for StyleHaven Boutique",
      "isActive": true,
      "sortOrder": 0
    },
    {
      "id": "cat_0063",
      "shopId": "shop_0061",
      "name": "Women's Wear",
      "slug": "women-s-wear",
      "description": "Women's Wear category for StyleHaven Boutique",
      "isActive": true,
      "sortOrder": 1
    },
    {
      "id": "cat_0064",
      "shopId": "shop_0061",
      "name": "Footwear",
      "slug": "footwear",
      "description": "Footwear category for StyleHaven Boutique",
      "isActive": true,
      "sortOrder": 2
    },
    {
      "id": "cat_0065",
      "shopId": "shop_0061",
      "name": "Bags",
      "slug": "bags",
      "description": "Bags category for StyleHaven Boutique",
      "isActive": true,
      "sortOrder": 3
    },
    {
      "id": "cat_0066",
      "shopId": "shop_0061",
      "name": "Jewelry",
      "slug": "jewelry",
      "description": "Jewelry category for StyleHaven Boutique",
      "isActive": true,
      "sortOrder": 4
    },
    {
      "id": "cat_0117",
      "shopId": "shop_0116",
      "name": "Furniture",
      "slug": "furniture",
      "description": "Furniture category for HomeNest Living",
      "isActive": true,
      "sortOrder": 0
    },
    {
      "id": "cat_0118",
      "shopId": "shop_0116",
      "name": "Lighting",
      "slug": "lighting",
      "description": "Lighting category for HomeNest Living",
      "isActive": true,
      "sortOrder": 1
    },
    {
      "id": "cat_0119",
      "shopId": "shop_0116",
      "name": "Kitchenware",
      "slug": "kitchenware",
      "description": "Kitchenware category for HomeNest Living",
      "isActive": true,
      "sortOrder": 2
    },
    {
      "id": "cat_0120",
      "shopId": "shop_0116",
      "name": "Bedding",
      "slug": "bedding",
      "description": "Bedding category for HomeNest Living",
      "isActive": true,
      "sortOrder": 3
    },
    {
      "id": "cat_0121",
      "shopId": "shop_0116",
      "name": "Decor",
      "slug": "decor",
      "description": "Decor category for HomeNest Living",
      "isActive": true,
      "sortOrder": 4
    },
    {
      "id": "cat_0171",
      "shopId": "shop_0170",
      "name": "Fruits",
      "slug": "fruits",
      "description": "Fruits category for GreenLeaf Organics",
      "isActive": true,
      "sortOrder": 0
    },
    {
      "id": "cat_0172",
      "shopId": "shop_0170",
      "name": "Vegetables",
      "slug": "vegetables",
      "description": "Vegetables category for GreenLeaf Organics",
      "isActive": true,
      "sortOrder": 1
    },
    {
      "id": "cat_0173",
      "shopId": "shop_0170",
      "name": "Dairy",
      "slug": "dairy",
      "description": "Dairy category for GreenLeaf Organics",
      "isActive": true,
      "sortOrder": 2
    },
    {
      "id": "cat_0174",
      "shopId": "shop_0170",
      "name": "Snacks",
      "slug": "snacks",
      "description": "Snacks category for GreenLeaf Organics",
      "isActive": true,
      "sortOrder": 3
    },
    {
      "id": "cat_0175",
      "shopId": "shop_0170",
      "name": "Beverages",
      "slug": "beverages",
      "description": "Beverages category for GreenLeaf Organics",
      "isActive": true,
      "sortOrder": 4
    },
    {
      "id": "cat_0221",
      "shopId": "shop_0220",
      "name": "Gym Equipment",
      "slug": "gym-equipment",
      "description": "Gym Equipment category for FitPro Sports",
      "isActive": true,
      "sortOrder": 0
    },
    {
      "id": "cat_0222",
      "shopId": "shop_0220",
      "name": "Running Gear",
      "slug": "running-gear",
      "description": "Running Gear category for FitPro Sports",
      "isActive": true,
      "sortOrder": 1
    },
    {
      "id": "cat_0223",
      "shopId": "shop_0220",
      "name": "Yoga",
      "slug": "yoga",
      "description": "Yoga category for FitPro Sports",
      "isActive": true,
      "sortOrder": 2
    },
    {
      "id": "cat_0224",
      "shopId": "shop_0220",
      "name": "Cycling",
      "slug": "cycling",
      "description": "Cycling category for FitPro Sports",
      "isActive": true,
      "sortOrder": 3
    },
    {
      "id": "cat_0225",
      "shopId": "shop_0220",
      "name": "Outdoor",
      "slug": "outdoor",
      "description": "Outdoor category for FitPro Sports",
      "isActive": true,
      "sortOrder": 4
    },
    {
      "id": "cat_0275",
      "shopId": "shop_0274",
      "name": "Fiction",
      "slug": "fiction",
      "description": "Fiction category for BookWorm Haven",
      "isActive": true,
      "sortOrder": 0
    },
    {
      "id": "cat_0276",
      "shopId": "shop_0274",
      "name": "Non-Fiction",
      "slug": "non-fiction",
      "description": "Non-Fiction category for BookWorm Haven",
      "isActive": true,
      "sortOrder": 1
    },
    {
      "id": "cat_0277",
      "shopId": "shop_0274",
      "name": "Academic",
      "slug": "academic",
      "description": "Academic category for BookWorm Haven",
      "isActive": true,
      "sortOrder": 2
    },
    {
      "id": "cat_0278",
      "shopId": "shop_0274",
      "name": "Children's Books",
      "slug": "children-s-books",
      "description": "Children's Books category for BookWorm Haven",
      "isActive": true,
      "sortOrder": 3
    },
    {
      "id": "cat_0279",
      "shopId": "shop_0274",
      "name": "Comics",
      "slug": "comics",
      "description": "Comics category for BookWorm Haven",
      "isActive": true,
      "sortOrder": 4
    },
    {
      "id": "cat_0324",
      "shopId": "shop_0323",
      "name": "Dog Food",
      "slug": "dog-food",
      "description": "Dog Food category for PetPals Store",
      "isActive": true,
      "sortOrder": 0
    },
    {
      "id": "cat_0325",
      "shopId": "shop_0323",
      "name": "Cat Food",
      "slug": "cat-food",
      "description": "Cat Food category for PetPals Store",
      "isActive": true,
      "sortOrder": 1
    },
    {
      "id": "cat_0326",
      "shopId": "shop_0323",
      "name": "Toys",
      "slug": "toys",
      "description": "Toys category for PetPals Store",
      "isActive": true,
      "sortOrder": 2
    },
    {
      "id": "cat_0327",
      "shopId": "shop_0323",
      "name": "Grooming",
      "slug": "grooming",
      "description": "Grooming category for PetPals Store",
      "isActive": true,
      "sortOrder": 3
    },
    {
      "id": "cat_0328",
      "shopId": "shop_0323",
      "name": "Health",
      "slug": "health",
      "description": "Health category for PetPals Store",
      "isActive": true,
      "sortOrder": 4
    },
    {
      "id": "cat_0374",
      "shopId": "shop_0373",
      "name": "Skincare",
      "slug": "skincare",
      "description": "Skincare category for BeautyGlow Cosmetics",
      "isActive": true,
      "sortOrder": 0
    },
    {
      "id": "cat_0375",
      "shopId": "shop_0373",
      "name": "Makeup",
      "slug": "makeup",
      "description": "Makeup category for BeautyGlow Cosmetics",
      "isActive": true,
      "sortOrder": 1
    },
    {
      "id": "cat_0376",
      "shopId": "shop_0373",
      "name": "Haircare",
      "slug": "haircare",
      "description": "Haircare category for BeautyGlow Cosmetics",
      "isActive": true,
      "sortOrder": 2
    },
    {
      "id": "cat_0377",
      "shopId": "shop_0373",
      "name": "Fragrance",
      "slug": "fragrance",
      "description": "Fragrance category for BeautyGlow Cosmetics",
      "isActive": true,
      "sortOrder": 3
    },
    {
      "id": "cat_0378",
      "shopId": "shop_0373",
      "name": "Tools",
      "slug": "tools",
      "description": "Tools category for BeautyGlow Cosmetics",
      "isActive": true,
      "sortOrder": 4
    },
    {
      "id": "cat_0428",
      "shopId": "shop_0427",
      "name": "Action Figures",
      "slug": "action-figures",
      "description": "Action Figures category for KidZone Toys",
      "isActive": true,
      "sortOrder": 0
    },
    {
      "id": "cat_0429",
      "shopId": "shop_0427",
      "name": "Board Games",
      "slug": "board-games",
      "description": "Board Games category for KidZone Toys",
      "isActive": true,
      "sortOrder": 1
    },
    {
      "id": "cat_0430",
      "shopId": "shop_0427",
      "name": "Puzzles",
      "slug": "puzzles",
      "description": "Puzzles category for KidZone Toys",
      "isActive": true,
      "sortOrder": 2
    },
    {
      "id": "cat_0431",
      "shopId": "shop_0427",
      "name": "Dolls",
      "slug": "dolls",
      "description": "Dolls category for KidZone Toys",
      "isActive": true,
      "sortOrder": 3
    },
    {
      "id": "cat_0432",
      "shopId": "shop_0427",
      "name": "STEM Kits",
      "slug": "stem-kits",
      "description": "STEM Kits category for KidZone Toys",
      "isActive": true,
      "sortOrder": 4
    },
    {
      "id": "cat_0478",
      "shopId": "shop_0477",
      "name": "Smartphones",
      "slug": "smartphones",
      "description": "Smartphones category for GadgetWorld Hub",
      "isActive": true,
      "sortOrder": 0
    },
    {
      "id": "cat_0479",
      "shopId": "shop_0477",
      "name": "Laptops",
      "slug": "laptops",
      "description": "Laptops category for GadgetWorld Hub",
      "isActive": true,
      "sortOrder": 1
    },
    {
      "id": "cat_0480",
      "shopId": "shop_0477",
      "name": "Audio",
      "slug": "audio",
      "description": "Audio category for GadgetWorld Hub",
      "isActive": true,
      "sortOrder": 2
    },
    {
      "id": "cat_0481",
      "shopId": "shop_0477",
      "name": "Wearables",
      "slug": "wearables",
      "description": "Wearables category for GadgetWorld Hub",
      "isActive": true,
      "sortOrder": 3
    },
    {
      "id": "cat_0482",
      "shopId": "shop_0477",
      "name": "Accessories",
      "slug": "accessories",
      "description": "Accessories category for GadgetWorld Hub",
      "isActive": true,
      "sortOrder": 4
    }
  ],
  "brands": [
    {
      "id": "brand_0013",
      "shopId": "shop_0007",
      "name": "Apple",
      "slug": "apple",
      "description": "Apple products",
      "isActive": true
    },
    {
      "id": "brand_0014",
      "shopId": "shop_0007",
      "name": "Samsung",
      "slug": "samsung",
      "description": "Samsung products",
      "isActive": true
    },
    {
      "id": "brand_0015",
      "shopId": "shop_0007",
      "name": "Sony",
      "slug": "sony",
      "description": "Sony products",
      "isActive": true
    },
    {
      "id": "brand_0016",
      "shopId": "shop_0007",
      "name": "Bose",
      "slug": "bose",
      "description": "Bose products",
      "isActive": true
    },
    {
      "id": "brand_0017",
      "shopId": "shop_0007",
      "name": "Anker",
      "slug": "anker",
      "description": "Anker products",
      "isActive": true
    },
    {
      "id": "brand_0067",
      "shopId": "shop_0061",
      "name": "Zara",
      "slug": "zara",
      "description": "Zara products",
      "isActive": true
    },
    {
      "id": "brand_0068",
      "shopId": "shop_0061",
      "name": "H&M",
      "slug": "h-m",
      "description": "H&M products",
      "isActive": true
    },
    {
      "id": "brand_0069",
      "shopId": "shop_0061",
      "name": "Nike",
      "slug": "nike",
      "description": "Nike products",
      "isActive": true
    },
    {
      "id": "brand_0070",
      "shopId": "shop_0061",
      "name": "Gucci",
      "slug": "gucci",
      "description": "Gucci products",
      "isActive": true
    },
    {
      "id": "brand_0071",
      "shopId": "shop_0061",
      "name": "Levi's",
      "slug": "levi-s",
      "description": "Levi's products",
      "isActive": true
    },
    {
      "id": "brand_0122",
      "shopId": "shop_0116",
      "name": "IKEA",
      "slug": "ikea",
      "description": "IKEA products",
      "isActive": true
    },
    {
      "id": "brand_0123",
      "shopId": "shop_0116",
      "name": "West Elm",
      "slug": "west-elm",
      "description": "West Elm products",
      "isActive": true
    },
    {
      "id": "brand_0124",
      "shopId": "shop_0116",
      "name": "Pottery Barn",
      "slug": "pottery-barn",
      "description": "Pottery Barn products",
      "isActive": true
    },
    {
      "id": "brand_0125",
      "shopId": "shop_0116",
      "name": "Crate & Barrel",
      "slug": "crate-barrel",
      "description": "Crate & Barrel products",
      "isActive": true
    },
    {
      "id": "brand_0126",
      "shopId": "shop_0116",
      "name": "Muji",
      "slug": "muji",
      "description": "Muji products",
      "isActive": true
    },
    {
      "id": "brand_0176",
      "shopId": "shop_0170",
      "name": "Whole Foods",
      "slug": "whole-foods",
      "description": "Whole Foods products",
      "isActive": true
    },
    {
      "id": "brand_0177",
      "shopId": "shop_0170",
      "name": "Organic Valley",
      "slug": "organic-valley",
      "description": "Organic Valley products",
      "isActive": true
    },
    {
      "id": "brand_0178",
      "shopId": "shop_0170",
      "name": "Nature's Path",
      "slug": "nature-s-path",
      "description": "Nature's Path products",
      "isActive": true
    },
    {
      "id": "brand_0179",
      "shopId": "shop_0170",
      "name": "Bob's Red Mill",
      "slug": "bob-s-red-mill",
      "description": "Bob's Red Mill products",
      "isActive": true
    },
    {
      "id": "brand_0180",
      "shopId": "shop_0170",
      "name": "Earthbound",
      "slug": "earthbound",
      "description": "Earthbound products",
      "isActive": true
    },
    {
      "id": "brand_0226",
      "shopId": "shop_0220",
      "name": "Nike",
      "slug": "nike",
      "description": "Nike products",
      "isActive": true
    },
    {
      "id": "brand_0227",
      "shopId": "shop_0220",
      "name": "Adidas",
      "slug": "adidas",
      "description": "Adidas products",
      "isActive": true
    },
    {
      "id": "brand_0228",
      "shopId": "shop_0220",
      "name": "Under Armour",
      "slug": "under-armour",
      "description": "Under Armour products",
      "isActive": true
    },
    {
      "id": "brand_0229",
      "shopId": "shop_0220",
      "name": "Reebok",
      "slug": "reebok",
      "description": "Reebok products",
      "isActive": true
    },
    {
      "id": "brand_0230",
      "shopId": "shop_0220",
      "name": "Puma",
      "slug": "puma",
      "description": "Puma products",
      "isActive": true
    },
    {
      "id": "brand_0280",
      "shopId": "shop_0274",
      "name": "Penguin",
      "slug": "penguin",
      "description": "Penguin products",
      "isActive": true
    },
    {
      "id": "brand_0281",
      "shopId": "shop_0274",
      "name": "HarperCollins",
      "slug": "harpercollins",
      "description": "HarperCollins products",
      "isActive": true
    },
    {
      "id": "brand_0282",
      "shopId": "shop_0274",
      "name": "Simon & Schuster",
      "slug": "simon-schuster",
      "description": "Simon & Schuster products",
      "isActive": true
    },
    {
      "id": "brand_0283",
      "shopId": "shop_0274",
      "name": "Scholastic",
      "slug": "scholastic",
      "description": "Scholastic products",
      "isActive": true
    },
    {
      "id": "brand_0284",
      "shopId": "shop_0274",
      "name": "O'Reilly",
      "slug": "o-reilly",
      "description": "O'Reilly products",
      "isActive": true
    },
    {
      "id": "brand_0329",
      "shopId": "shop_0323",
      "name": "Royal Canin",
      "slug": "royal-canin",
      "description": "Royal Canin products",
      "isActive": true
    },
    {
      "id": "brand_0330",
      "shopId": "shop_0323",
      "name": "Blue Buffalo",
      "slug": "blue-buffalo",
      "description": "Blue Buffalo products",
      "isActive": true
    },
    {
      "id": "brand_0331",
      "shopId": "shop_0323",
      "name": "Purina",
      "slug": "purina",
      "description": "Purina products",
      "isActive": true
    },
    {
      "id": "brand_0332",
      "shopId": "shop_0323",
      "name": "Hill's",
      "slug": "hill-s",
      "description": "Hill's products",
      "isActive": true
    },
    {
      "id": "brand_0333",
      "shopId": "shop_0323",
      "name": "KONG",
      "slug": "kong",
      "description": "KONG products",
      "isActive": true
    },
    {
      "id": "brand_0379",
      "shopId": "shop_0373",
      "name": "L'Oreal",
      "slug": "l-oreal",
      "description": "L'Oreal products",
      "isActive": true
    },
    {
      "id": "brand_0380",
      "shopId": "shop_0373",
      "name": "Estee Lauder",
      "slug": "estee-lauder",
      "description": "Estee Lauder products",
      "isActive": true
    },
    {
      "id": "brand_0381",
      "shopId": "shop_0373",
      "name": "Clinique",
      "slug": "clinique",
      "description": "Clinique products",
      "isActive": true
    },
    {
      "id": "brand_0382",
      "shopId": "shop_0373",
      "name": "MAC",
      "slug": "mac",
      "description": "MAC products",
      "isActive": true
    },
    {
      "id": "brand_0383",
      "shopId": "shop_0373",
      "name": "Neutrogena",
      "slug": "neutrogena",
      "description": "Neutrogena products",
      "isActive": true
    },
    {
      "id": "brand_0433",
      "shopId": "shop_0427",
      "name": "LEGO",
      "slug": "lego",
      "description": "LEGO products",
      "isActive": true
    },
    {
      "id": "brand_0434",
      "shopId": "shop_0427",
      "name": "Hasbro",
      "slug": "hasbro",
      "description": "Hasbro products",
      "isActive": true
    },
    {
      "id": "brand_0435",
      "shopId": "shop_0427",
      "name": "Mattel",
      "slug": "mattel",
      "description": "Mattel products",
      "isActive": true
    },
    {
      "id": "brand_0436",
      "shopId": "shop_0427",
      "name": "Fisher-Price",
      "slug": "fisher-price",
      "description": "Fisher-Price products",
      "isActive": true
    },
    {
      "id": "brand_0437",
      "shopId": "shop_0427",
      "name": "Melissa & Doug",
      "slug": "melissa-doug",
      "description": "Melissa & Doug products",
      "isActive": true
    },
    {
      "id": "brand_0483",
      "shopId": "shop_0477",
      "name": "Apple",
      "slug": "apple",
      "description": "Apple products",
      "isActive": true
    },
    {
      "id": "brand_0484",
      "shopId": "shop_0477",
      "name": "Samsung",
      "slug": "samsung",
      "description": "Samsung products",
      "isActive": true
    },
    {
      "id": "brand_0485",
      "shopId": "shop_0477",
      "name": "Sony",
      "slug": "sony",
      "description": "Sony products",
      "isActive": true
    },
    {
      "id": "brand_0486",
      "shopId": "shop_0477",
      "name": "Bose",
      "slug": "bose",
      "description": "Bose products",
      "isActive": true
    },
    {
      "id": "brand_0487",
      "shopId": "shop_0477",
      "name": "Anker",
      "slug": "anker",
      "description": "Anker products",
      "isActive": true
    }
  ],
  "tags": [
    {
      "id": "tag_0018",
      "shopId": "shop_0007",
      "name": "bestseller",
      "slug": "bestseller",
      "description": "bestseller tag",
      "isActive": true,
      "sortOrder": 0
    },
    {
      "id": "tag_0019",
      "shopId": "shop_0007",
      "name": "new arrival",
      "slug": "new-arrival",
      "description": "new-arrival tag",
      "isActive": true,
      "sortOrder": 1
    },
    {
      "id": "tag_0020",
      "shopId": "shop_0007",
      "name": "trending",
      "slug": "trending",
      "description": "trending tag",
      "isActive": true,
      "sortOrder": 2
    },
    {
      "id": "tag_0021",
      "shopId": "shop_0007",
      "name": "limited edition",
      "slug": "limited-edition",
      "description": "limited-edition tag",
      "isActive": true,
      "sortOrder": 3
    },
    {
      "id": "tag_0022",
      "shopId": "shop_0007",
      "name": "sale",
      "slug": "sale",
      "description": "sale tag",
      "isActive": true,
      "sortOrder": 4
    },
    {
      "id": "tag_0072",
      "shopId": "shop_0061",
      "name": "summer collection",
      "slug": "summer-collection",
      "description": "summer-collection tag",
      "isActive": true,
      "sortOrder": 0
    },
    {
      "id": "tag_0073",
      "shopId": "shop_0061",
      "name": "winter collection",
      "slug": "winter-collection",
      "description": "winter-collection tag",
      "isActive": true,
      "sortOrder": 1
    },
    {
      "id": "tag_0074",
      "shopId": "shop_0061",
      "name": "bestseller",
      "slug": "bestseller",
      "description": "bestseller tag",
      "isActive": true,
      "sortOrder": 2
    },
    {
      "id": "tag_0075",
      "shopId": "shop_0061",
      "name": "eco friendly",
      "slug": "eco-friendly",
      "description": "eco-friendly tag",
      "isActive": true,
      "sortOrder": 3
    },
    {
      "id": "tag_0076",
      "shopId": "shop_0061",
      "name": "premium",
      "slug": "premium",
      "description": "premium tag",
      "isActive": true,
      "sortOrder": 4
    },
    {
      "id": "tag_0127",
      "shopId": "shop_0116",
      "name": "handmade",
      "slug": "handmade",
      "description": "handmade tag",
      "isActive": true,
      "sortOrder": 0
    },
    {
      "id": "tag_0128",
      "shopId": "shop_0116",
      "name": "sustainable",
      "slug": "sustainable",
      "description": "sustainable tag",
      "isActive": true,
      "sortOrder": 1
    },
    {
      "id": "tag_0129",
      "shopId": "shop_0116",
      "name": "modern",
      "slug": "modern",
      "description": "modern tag",
      "isActive": true,
      "sortOrder": 2
    },
    {
      "id": "tag_0130",
      "shopId": "shop_0116",
      "name": "vintage",
      "slug": "vintage",
      "description": "vintage tag",
      "isActive": true,
      "sortOrder": 3
    },
    {
      "id": "tag_0131",
      "shopId": "shop_0116",
      "name": "clearance",
      "slug": "clearance",
      "description": "clearance tag",
      "isActive": true,
      "sortOrder": 4
    },
    {
      "id": "tag_0181",
      "shopId": "shop_0170",
      "name": "organic",
      "slug": "organic",
      "description": "organic tag",
      "isActive": true,
      "sortOrder": 0
    },
    {
      "id": "tag_0182",
      "shopId": "shop_0170",
      "name": "gluten free",
      "slug": "gluten-free",
      "description": "gluten-free tag",
      "isActive": true,
      "sortOrder": 1
    },
    {
      "id": "tag_0183",
      "shopId": "shop_0170",
      "name": "vegan",
      "slug": "vegan",
      "description": "vegan tag",
      "isActive": true,
      "sortOrder": 2
    },
    {
      "id": "tag_0184",
      "shopId": "shop_0170",
      "name": "sugar free",
      "slug": "sugar-free",
      "description": "sugar-free tag",
      "isActive": true,
      "sortOrder": 3
    },
    {
      "id": "tag_0185",
      "shopId": "shop_0170",
      "name": "farm fresh",
      "slug": "farm-fresh",
      "description": "farm-fresh tag",
      "isActive": true,
      "sortOrder": 4
    },
    {
      "id": "tag_0231",
      "shopId": "shop_0220",
      "name": "pro grade",
      "slug": "pro-grade",
      "description": "pro-grade tag",
      "isActive": true,
      "sortOrder": 0
    },
    {
      "id": "tag_0232",
      "shopId": "shop_0220",
      "name": "lightweight",
      "slug": "lightweight",
      "description": "lightweight tag",
      "isActive": true,
      "sortOrder": 1
    },
    {
      "id": "tag_0233",
      "shopId": "shop_0220",
      "name": "durable",
      "slug": "durable",
      "description": "durable tag",
      "isActive": true,
      "sortOrder": 2
    },
    {
      "id": "tag_0234",
      "shopId": "shop_0220",
      "name": "compact",
      "slug": "compact",
      "description": "compact tag",
      "isActive": true,
      "sortOrder": 3
    },
    {
      "id": "tag_0235",
      "shopId": "shop_0220",
      "name": "bestseller",
      "slug": "bestseller",
      "description": "bestseller tag",
      "isActive": true,
      "sortOrder": 4
    },
    {
      "id": "tag_0285",
      "shopId": "shop_0274",
      "name": "award winning",
      "slug": "award-winning",
      "description": "award-winning tag",
      "isActive": true,
      "sortOrder": 0
    },
    {
      "id": "tag_0286",
      "shopId": "shop_0274",
      "name": "bestseller",
      "slug": "bestseller",
      "description": "bestseller tag",
      "isActive": true,
      "sortOrder": 1
    },
    {
      "id": "tag_0287",
      "shopId": "shop_0274",
      "name": "new release",
      "slug": "new-release",
      "description": "new-release tag",
      "isActive": true,
      "sortOrder": 2
    },
    {
      "id": "tag_0288",
      "shopId": "shop_0274",
      "name": "classic",
      "slug": "classic",
      "description": "classic tag",
      "isActive": true,
      "sortOrder": 3
    },
    {
      "id": "tag_0289",
      "shopId": "shop_0274",
      "name": "signed copy",
      "slug": "signed-copy",
      "description": "signed-copy tag",
      "isActive": true,
      "sortOrder": 4
    },
    {
      "id": "tag_0334",
      "shopId": "shop_0323",
      "name": "natural",
      "slug": "natural",
      "description": "natural tag",
      "isActive": true,
      "sortOrder": 0
    },
    {
      "id": "tag_0335",
      "shopId": "shop_0323",
      "name": "grain free",
      "slug": "grain-free",
      "description": "grain-free tag",
      "isActive": true,
      "sortOrder": 1
    },
    {
      "id": "tag_0336",
      "shopId": "shop_0323",
      "name": "vet recommended",
      "slug": "vet-recommended",
      "description": "vet-recommended tag",
      "isActive": true,
      "sortOrder": 2
    },
    {
      "id": "tag_0337",
      "shopId": "shop_0323",
      "name": "eco friendly",
      "slug": "eco-friendly",
      "description": "eco-friendly tag",
      "isActive": true,
      "sortOrder": 3
    },
    {
      "id": "tag_0338",
      "shopId": "shop_0323",
      "name": "premium",
      "slug": "premium",
      "description": "premium tag",
      "isActive": true,
      "sortOrder": 4
    },
    {
      "id": "tag_0384",
      "shopId": "shop_0373",
      "name": "cruelty free",
      "slug": "cruelty-free",
      "description": "cruelty-free tag",
      "isActive": true,
      "sortOrder": 0
    },
    {
      "id": "tag_0385",
      "shopId": "shop_0373",
      "name": "vegan",
      "slug": "vegan",
      "description": "vegan tag",
      "isActive": true,
      "sortOrder": 1
    },
    {
      "id": "tag_0386",
      "shopId": "shop_0373",
      "name": "organic",
      "slug": "organic",
      "description": "organic tag",
      "isActive": true,
      "sortOrder": 2
    },
    {
      "id": "tag_0387",
      "shopId": "shop_0373",
      "name": "dermatologist tested",
      "slug": "dermatologist-tested",
      "description": "dermatologist-tested tag",
      "isActive": true,
      "sortOrder": 3
    },
    {
      "id": "tag_0388",
      "shopId": "shop_0373",
      "name": "anti aging",
      "slug": "anti-aging",
      "description": "anti-aging tag",
      "isActive": true,
      "sortOrder": 4
    },
    {
      "id": "tag_0438",
      "shopId": "shop_0427",
      "name": "educational",
      "slug": "educational",
      "description": "educational tag",
      "isActive": true,
      "sortOrder": 0
    },
    {
      "id": "tag_0439",
      "shopId": "shop_0427",
      "name": "eco friendly",
      "slug": "eco-friendly",
      "description": "eco-friendly tag",
      "isActive": true,
      "sortOrder": 1
    },
    {
      "id": "tag_0440",
      "shopId": "shop_0427",
      "name": "award winning",
      "slug": "award-winning",
      "description": "award-winning tag",
      "isActive": true,
      "sortOrder": 2
    },
    {
      "id": "tag_0441",
      "shopId": "shop_0427",
      "name": "ages 3 plus",
      "slug": "ages-3-plus",
      "description": "ages-3-plus tag",
      "isActive": true,
      "sortOrder": 3
    },
    {
      "id": "tag_0442",
      "shopId": "shop_0427",
      "name": "stem",
      "slug": "stem",
      "description": "stem tag",
      "isActive": true,
      "sortOrder": 4
    },
    {
      "id": "tag_0488",
      "shopId": "shop_0477",
      "name": "bestseller",
      "slug": "bestseller",
      "description": "bestseller tag",
      "isActive": true,
      "sortOrder": 0
    },
    {
      "id": "tag_0489",
      "shopId": "shop_0477",
      "name": "new arrival",
      "slug": "new-arrival",
      "description": "new-arrival tag",
      "isActive": true,
      "sortOrder": 1
    },
    {
      "id": "tag_0490",
      "shopId": "shop_0477",
      "name": "trending",
      "slug": "trending",
      "description": "trending tag",
      "isActive": true,
      "sortOrder": 2
    },
    {
      "id": "tag_0491",
      "shopId": "shop_0477",
      "name": "limited edition",
      "slug": "limited-edition",
      "description": "limited-edition tag",
      "isActive": true,
      "sortOrder": 3
    },
    {
      "id": "tag_0492",
      "shopId": "shop_0477",
      "name": "sale",
      "slug": "sale",
      "description": "sale tag",
      "isActive": true,
      "sortOrder": 4
    }
  ],
  "attributes": [
    {
      "id": "attr_0023",
      "shopId": "shop_0007",
      "name": "Color",
      "slug": "color",
      "type": "color",
      "values": [
        {
          "id": "aval_0024",
          "name": "Black",
          "value": "#000000"
        },
        {
          "id": "aval_0025",
          "name": "Silver",
          "value": "#C0C0C0"
        },
        {
          "id": "aval_0026",
          "name": "White",
          "value": "#FFFFFF"
        }
      ]
    },
    {
      "id": "attr_0027",
      "shopId": "shop_0007",
      "name": "Storage",
      "slug": "storage",
      "type": "select",
      "values": [
        {
          "id": "aval_0028",
          "name": "64GB",
          "value": "64GB"
        },
        {
          "id": "aval_0029",
          "name": "128GB",
          "value": "128GB"
        },
        {
          "id": "aval_0030",
          "name": "256GB",
          "value": "256GB"
        }
      ]
    },
    {
      "id": "attr_0077",
      "shopId": "shop_0061",
      "name": "Size",
      "slug": "size",
      "type": "label",
      "values": [
        {
          "id": "aval_0078",
          "name": "S",
          "value": "S"
        },
        {
          "id": "aval_0079",
          "name": "M",
          "value": "M"
        },
        {
          "id": "aval_0080",
          "name": "L",
          "value": "L"
        },
        {
          "id": "aval_0081",
          "name": "XL",
          "value": "XL"
        }
      ]
    },
    {
      "id": "attr_0082",
      "shopId": "shop_0061",
      "name": "Color",
      "slug": "color",
      "type": "color",
      "values": [
        {
          "id": "aval_0083",
          "name": "Red",
          "value": "#FF0000"
        },
        {
          "id": "aval_0084",
          "name": "Blue",
          "value": "#0000FF"
        },
        {
          "id": "aval_0085",
          "name": "Black",
          "value": "#000000"
        }
      ]
    },
    {
      "id": "attr_0132",
      "shopId": "shop_0116",
      "name": "Material",
      "slug": "material",
      "type": "select",
      "values": [
        {
          "id": "aval_0133",
          "name": "Wood",
          "value": "Wood"
        },
        {
          "id": "aval_0134",
          "name": "Metal",
          "value": "Metal"
        },
        {
          "id": "aval_0135",
          "name": "Fabric",
          "value": "Fabric"
        }
      ]
    },
    {
      "id": "attr_0136",
      "shopId": "shop_0116",
      "name": "Color",
      "slug": "color",
      "type": "color",
      "values": [
        {
          "id": "aval_0137",
          "name": "Oak",
          "value": "#C19A6B"
        },
        {
          "id": "aval_0138",
          "name": "Walnut",
          "value": "#5C4033"
        },
        {
          "id": "aval_0139",
          "name": "White",
          "value": "#FFFFFF"
        }
      ]
    },
    {
      "id": "attr_0186",
      "shopId": "shop_0170",
      "name": "Weight",
      "slug": "weight",
      "type": "select",
      "values": [
        {
          "id": "aval_0187",
          "name": "250g",
          "value": "250g"
        },
        {
          "id": "aval_0188",
          "name": "500g",
          "value": "500g"
        },
        {
          "id": "aval_0189",
          "name": "1kg",
          "value": "1kg"
        }
      ]
    },
    {
      "id": "attr_0236",
      "shopId": "shop_0220",
      "name": "Size",
      "slug": "size",
      "type": "label",
      "values": [
        {
          "id": "aval_0237",
          "name": "S",
          "value": "S"
        },
        {
          "id": "aval_0238",
          "name": "M",
          "value": "M"
        },
        {
          "id": "aval_0239",
          "name": "L",
          "value": "L"
        }
      ]
    },
    {
      "id": "attr_0240",
      "shopId": "shop_0220",
      "name": "Color",
      "slug": "color",
      "type": "color",
      "values": [
        {
          "id": "aval_0241",
          "name": "Black",
          "value": "#000000"
        },
        {
          "id": "aval_0242",
          "name": "Red",
          "value": "#FF0000"
        },
        {
          "id": "aval_0243",
          "name": "Blue",
          "value": "#0000FF"
        }
      ]
    },
    {
      "id": "attr_0290",
      "shopId": "shop_0274",
      "name": "Format",
      "slug": "format",
      "type": "select",
      "values": [
        {
          "id": "aval_0291",
          "name": "Paperback",
          "value": "Paperback"
        },
        {
          "id": "aval_0292",
          "name": "Hardcover",
          "value": "Hardcover"
        }
      ]
    },
    {
      "id": "attr_0339",
      "shopId": "shop_0323",
      "name": "Size",
      "slug": "size",
      "type": "select",
      "values": [
        {
          "id": "aval_0340",
          "name": "Small",
          "value": "Small"
        },
        {
          "id": "aval_0341",
          "name": "Medium",
          "value": "Medium"
        },
        {
          "id": "aval_0342",
          "name": "Large",
          "value": "Large"
        }
      ]
    },
    {
      "id": "attr_0389",
      "shopId": "shop_0373",
      "name": "Shade",
      "slug": "shade",
      "type": "color",
      "values": [
        {
          "id": "aval_0390",
          "name": "Light",
          "value": "#FDEBD0"
        },
        {
          "id": "aval_0391",
          "name": "Medium",
          "value": "#D4A574"
        },
        {
          "id": "aval_0392",
          "name": "Dark",
          "value": "#8B4513"
        }
      ]
    },
    {
      "id": "attr_0393",
      "shopId": "shop_0373",
      "name": "Size",
      "slug": "size",
      "type": "select",
      "values": [
        {
          "id": "aval_0394",
          "name": "30ml",
          "value": "30ml"
        },
        {
          "id": "aval_0395",
          "name": "50ml",
          "value": "50ml"
        },
        {
          "id": "aval_0396",
          "name": "100ml",
          "value": "100ml"
        }
      ]
    },
    {
      "id": "attr_0443",
      "shopId": "shop_0427",
      "name": "Age Group",
      "slug": "age-group",
      "type": "label",
      "values": [
        {
          "id": "aval_0444",
          "name": "3-5 Years",
          "value": "3-5"
        },
        {
          "id": "aval_0445",
          "name": "6-8 Years",
          "value": "6-8"
        },
        {
          "id": "aval_0446",
          "name": "9-12 Years",
          "value": "9-12"
        }
      ]
    },
    {
      "id": "attr_0493",
      "shopId": "shop_0477",
      "name": "Color",
      "slug": "color",
      "type": "color",
      "values": [
        {
          "id": "aval_0494",
          "name": "Black",
          "value": "#000000"
        },
        {
          "id": "aval_0495",
          "name": "Silver",
          "value": "#C0C0C0"
        },
        {
          "id": "aval_0496",
          "name": "White",
          "value": "#FFFFFF"
        }
      ]
    },
    {
      "id": "attr_0497",
      "shopId": "shop_0477",
      "name": "Storage",
      "slug": "storage",
      "type": "select",
      "values": [
        {
          "id": "aval_0498",
          "name": "64GB",
          "value": "64GB"
        },
        {
          "id": "aval_0499",
          "name": "128GB",
          "value": "128GB"
        },
        {
          "id": "aval_0500",
          "name": "256GB",
          "value": "256GB"
        }
      ]
    }
  ],
  "taxes": [
    {
      "id": "tax_0031",
      "shopId": "shop_0007",
      "name": "Standard Tax",
      "rate": "10.00",
      "country": "US",
      "isCompound": false,
      "isActive": true
    },
    {
      "id": "tax_0032",
      "shopId": "shop_0007",
      "name": "Reduced Tax",
      "rate": "5.00",
      "country": "US",
      "isCompound": false,
      "isActive": true
    },
    {
      "id": "tax_0086",
      "shopId": "shop_0061",
      "name": "Standard Tax",
      "rate": "10.00",
      "country": "US",
      "isCompound": false,
      "isActive": true
    },
    {
      "id": "tax_0087",
      "shopId": "shop_0061",
      "name": "Reduced Tax",
      "rate": "5.00",
      "country": "US",
      "isCompound": false,
      "isActive": true
    },
    {
      "id": "tax_0140",
      "shopId": "shop_0116",
      "name": "Standard Tax",
      "rate": "10.00",
      "country": "US",
      "isCompound": false,
      "isActive": true
    },
    {
      "id": "tax_0141",
      "shopId": "shop_0116",
      "name": "Reduced Tax",
      "rate": "5.00",
      "country": "US",
      "isCompound": false,
      "isActive": true
    },
    {
      "id": "tax_0190",
      "shopId": "shop_0170",
      "name": "Standard Tax",
      "rate": "10.00",
      "country": "US",
      "isCompound": false,
      "isActive": true
    },
    {
      "id": "tax_0191",
      "shopId": "shop_0170",
      "name": "Reduced Tax",
      "rate": "5.00",
      "country": "US",
      "isCompound": false,
      "isActive": true
    },
    {
      "id": "tax_0244",
      "shopId": "shop_0220",
      "name": "Standard Tax",
      "rate": "10.00",
      "country": "US",
      "isCompound": false,
      "isActive": true
    },
    {
      "id": "tax_0245",
      "shopId": "shop_0220",
      "name": "Reduced Tax",
      "rate": "5.00",
      "country": "US",
      "isCompound": false,
      "isActive": true
    },
    {
      "id": "tax_0293",
      "shopId": "shop_0274",
      "name": "Standard Tax",
      "rate": "10.00",
      "country": "US",
      "isCompound": false,
      "isActive": true
    },
    {
      "id": "tax_0294",
      "shopId": "shop_0274",
      "name": "Reduced Tax",
      "rate": "5.00",
      "country": "US",
      "isCompound": false,
      "isActive": true
    },
    {
      "id": "tax_0343",
      "shopId": "shop_0323",
      "name": "Standard Tax",
      "rate": "10.00",
      "country": "US",
      "isCompound": false,
      "isActive": true
    },
    {
      "id": "tax_0344",
      "shopId": "shop_0323",
      "name": "Reduced Tax",
      "rate": "5.00",
      "country": "US",
      "isCompound": false,
      "isActive": true
    },
    {
      "id": "tax_0397",
      "shopId": "shop_0373",
      "name": "Standard Tax",
      "rate": "10.00",
      "country": "US",
      "isCompound": false,
      "isActive": true
    },
    {
      "id": "tax_0398",
      "shopId": "shop_0373",
      "name": "Reduced Tax",
      "rate": "5.00",
      "country": "US",
      "isCompound": false,
      "isActive": true
    },
    {
      "id": "tax_0447",
      "shopId": "shop_0427",
      "name": "Standard Tax",
      "rate": "10.00",
      "country": "US",
      "isCompound": false,
      "isActive": true
    },
    {
      "id": "tax_0448",
      "shopId": "shop_0427",
      "name": "Reduced Tax",
      "rate": "5.00",
      "country": "US",
      "isCompound": false,
      "isActive": true
    },
    {
      "id": "tax_0501",
      "shopId": "shop_0477",
      "name": "Standard Tax",
      "rate": "10.00",
      "country": "US",
      "isCompound": false,
      "isActive": true
    },
    {
      "id": "tax_0502",
      "shopId": "shop_0477",
      "name": "Reduced Tax",
      "rate": "5.00",
      "country": "US",
      "isCompound": false,
      "isActive": true
    }
  ],
  "shippingMethods": [
    {
      "id": "ship_0033",
      "shopId": "shop_0007",
      "name": "Standard Shipping",
      "description": "Regular delivery service",
      "price": "5.99",
      "duration": "5-7 business days",
      "isActive": true
    },
    {
      "id": "ship_0034",
      "shopId": "shop_0007",
      "name": "Express Shipping",
      "description": "Fast delivery service",
      "price": "14.99",
      "duration": "2-3 business days",
      "isActive": true
    },
    {
      "id": "ship_0035",
      "shopId": "shop_0007",
      "name": "Overnight Shipping",
      "description": "Next-day delivery",
      "price": "24.99",
      "duration": "1 business day",
      "isActive": true
    },
    {
      "id": "ship_0088",
      "shopId": "shop_0061",
      "name": "Standard Shipping",
      "description": "Regular delivery service",
      "price": "5.99",
      "duration": "5-7 business days",
      "isActive": true
    },
    {
      "id": "ship_0089",
      "shopId": "shop_0061",
      "name": "Express Shipping",
      "description": "Fast delivery service",
      "price": "14.99",
      "duration": "2-3 business days",
      "isActive": true
    },
    {
      "id": "ship_0090",
      "shopId": "shop_0061",
      "name": "Overnight Shipping",
      "description": "Next-day delivery",
      "price": "24.99",
      "duration": "1 business day",
      "isActive": true
    },
    {
      "id": "ship_0142",
      "shopId": "shop_0116",
      "name": "Standard Shipping",
      "description": "Regular delivery service",
      "price": "5.99",
      "duration": "5-7 business days",
      "isActive": true
    },
    {
      "id": "ship_0143",
      "shopId": "shop_0116",
      "name": "Express Shipping",
      "description": "Fast delivery service",
      "price": "14.99",
      "duration": "2-3 business days",
      "isActive": true
    },
    {
      "id": "ship_0144",
      "shopId": "shop_0116",
      "name": "Overnight Shipping",
      "description": "Next-day delivery",
      "price": "24.99",
      "duration": "1 business day",
      "isActive": true
    },
    {
      "id": "ship_0192",
      "shopId": "shop_0170",
      "name": "Standard Shipping",
      "description": "Regular delivery service",
      "price": "5.99",
      "duration": "5-7 business days",
      "isActive": true
    },
    {
      "id": "ship_0193",
      "shopId": "shop_0170",
      "name": "Express Shipping",
      "description": "Fast delivery service",
      "price": "14.99",
      "duration": "2-3 business days",
      "isActive": true
    },
    {
      "id": "ship_0194",
      "shopId": "shop_0170",
      "name": "Overnight Shipping",
      "description": "Next-day delivery",
      "price": "24.99",
      "duration": "1 business day",
      "isActive": true
    },
    {
      "id": "ship_0246",
      "shopId": "shop_0220",
      "name": "Standard Shipping",
      "description": "Regular delivery service",
      "price": "5.99",
      "duration": "5-7 business days",
      "isActive": true
    },
    {
      "id": "ship_0247",
      "shopId": "shop_0220",
      "name": "Express Shipping",
      "description": "Fast delivery service",
      "price": "14.99",
      "duration": "2-3 business days",
      "isActive": true
    },
    {
      "id": "ship_0248",
      "shopId": "shop_0220",
      "name": "Overnight Shipping",
      "description": "Next-day delivery",
      "price": "24.99",
      "duration": "1 business day",
      "isActive": true
    },
    {
      "id": "ship_0295",
      "shopId": "shop_0274",
      "name": "Standard Shipping",
      "description": "Regular delivery service",
      "price": "5.99",
      "duration": "5-7 business days",
      "isActive": true
    },
    {
      "id": "ship_0296",
      "shopId": "shop_0274",
      "name": "Express Shipping",
      "description": "Fast delivery service",
      "price": "14.99",
      "duration": "2-3 business days",
      "isActive": true
    },
    {
      "id": "ship_0297",
      "shopId": "shop_0274",
      "name": "Overnight Shipping",
      "description": "Next-day delivery",
      "price": "24.99",
      "duration": "1 business day",
      "isActive": true
    },
    {
      "id": "ship_0345",
      "shopId": "shop_0323",
      "name": "Standard Shipping",
      "description": "Regular delivery service",
      "price": "5.99",
      "duration": "5-7 business days",
      "isActive": true
    },
    {
      "id": "ship_0346",
      "shopId": "shop_0323",
      "name": "Express Shipping",
      "description": "Fast delivery service",
      "price": "14.99",
      "duration": "2-3 business days",
      "isActive": true
    },
    {
      "id": "ship_0347",
      "shopId": "shop_0323",
      "name": "Overnight Shipping",
      "description": "Next-day delivery",
      "price": "24.99",
      "duration": "1 business day",
      "isActive": true
    },
    {
      "id": "ship_0399",
      "shopId": "shop_0373",
      "name": "Standard Shipping",
      "description": "Regular delivery service",
      "price": "5.99",
      "duration": "5-7 business days",
      "isActive": true
    },
    {
      "id": "ship_0400",
      "shopId": "shop_0373",
      "name": "Express Shipping",
      "description": "Fast delivery service",
      "price": "14.99",
      "duration": "2-3 business days",
      "isActive": true
    },
    {
      "id": "ship_0401",
      "shopId": "shop_0373",
      "name": "Overnight Shipping",
      "description": "Next-day delivery",
      "price": "24.99",
      "duration": "1 business day",
      "isActive": true
    },
    {
      "id": "ship_0449",
      "shopId": "shop_0427",
      "name": "Standard Shipping",
      "description": "Regular delivery service",
      "price": "5.99",
      "duration": "5-7 business days",
      "isActive": true
    },
    {
      "id": "ship_0450",
      "shopId": "shop_0427",
      "name": "Express Shipping",
      "description": "Fast delivery service",
      "price": "14.99",
      "duration": "2-3 business days",
      "isActive": true
    },
    {
      "id": "ship_0451",
      "shopId": "shop_0427",
      "name": "Overnight Shipping",
      "description": "Next-day delivery",
      "price": "24.99",
      "duration": "1 business day",
      "isActive": true
    },
    {
      "id": "ship_0503",
      "shopId": "shop_0477",
      "name": "Standard Shipping",
      "description": "Regular delivery service",
      "price": "5.99",
      "duration": "5-7 business days",
      "isActive": true
    },
    {
      "id": "ship_0504",
      "shopId": "shop_0477",
      "name": "Express Shipping",
      "description": "Fast delivery service",
      "price": "14.99",
      "duration": "2-3 business days",
      "isActive": true
    },
    {
      "id": "ship_0505",
      "shopId": "shop_0477",
      "name": "Overnight Shipping",
      "description": "Next-day delivery",
      "price": "24.99",
      "duration": "1 business day",
      "isActive": true
    }
  ]
}